{
  "$schema": "https://raw.githubusercontent.com/jsonresume/resume-schema/v1.0.0/schema.json",
  "basics": {
    "name": "Shrey Pandey",
    "label": "Research Fellow at Microsoft Research",
    "image": "",
    "email": "shreypandey1509@gmail.com",
    "phone": "+91-9057261430",
    "url": "https://shreypandey.github.io",
    "location": {
      "address": "9, Lavelle Road",
      "postalCode": "KA 560001",
      "city": "Bengaluru",
      "countryCode": "IN",
      "region": "Karnataka"
    },
    "profiles": [
      {
        "network": "LinkedIn",
        "username": "shrey2076",
        "url": "https://www.linkedin.com/in/shrey2076/"
      },
      {
        "network": "Twitter",
        "username": "ShreyPandey1509",
        "url": "https://twitter.com/ShreyPandey1509"
      }
    ]
  },
  "work": [
    {
      "name": "Microsoft",
      "position": "Research Fellow",
      "startDate": "2024-01-31",
      "highlights": [],
      "summary": "Working on Programming with Representations which aims to redefine software methodology for the generative AI era, enabling professional software teams to process a high volume of changes, faster and better.",
      "url": "https://www.linkedin.com/company/1035",
      "location": "Bengaluru, India"
    },
    {
      "name": "Myntra",
      "position": "Senior Software Engineer",
      "startDate": "2023-04-30",
      "endDate": "2024-01-31",
      "highlights": [],
      "summary": null,
      "url": "https://www.linkedin.com/company/361348",
      "location": "Bengaluru, India"
    },
    {
      "name": "Myntra",
      "position": "Software Engineer",
      "startDate": "2021-06-30",
      "endDate": "2023-04-30",
      "highlights": [],
      "summary": null,
      "url": "https://www.linkedin.com/company/361348",
      "location": "Bengaluru, India"
    },
    {
      "name": "Stealth Startup",
      "position": "Software Developer",
      "startDate": "2020-03-31",
      "endDate": "2021-05-31",
      "highlights": [],
      "summary": null,
      "url": "https://www.linkedin.com/company/18583501",
      "location": "Remote"
    },
    {
      "name": "Myntra",
      "position": "Software Engineering Intern",
      "startDate": "2020-04-30",
      "endDate": "2020-07-31",
      "highlights": [
        "Developed an encoder-decoder-based generative model for preliminary image generation using Generative Adversarial Networks (GANs).",
        "Developed an image refinement model for processing the generated preliminary image to incorporate garment textures, ensuring accurate top-wear product replacement while retaining pose and body shape.",
        "The generated images were close to the Myntra image standards."
      ],
      "summary": "Designed and implemented a two-step framework for topwear product swapping in images.",
      "url": "https://www.linkedin.com/company/361348",
      "location": "Bengaluru, India"
    }
  ],
  "volunteer": [
    {
      "organization": "Hack36",
      "position": "Networking Lead",
      "startDate": "2021-01-31",
      "endDate": "2021-04-30",
      "summary": null,
      "highlights": [],
      "url": "https://www.linkedin.com/company/31091198"
    },
    {
      "organization": "Motilal Nehru National Institute Of Technology",
      "position": "Event Coordinator at Avishkar",
      "startDate": "2020-08-31",
      "endDate": "2020-11-30",
      "summary": null,
      "highlights": [],
      "url": "https://www.linkedin.com/company/15105506"
    },
    {
      "organization": "Motilal Nehru National Institute Of Technology",
      "position": "Computer Club Volunteer",
      "startDate": "2020-03-31",
      "endDate": "2021-04-30",
      "summary": null,
      "highlights": [],
      "url": "https://www.linkedin.com/company/15105506"
    }
  ],
  "education": [
    {
      "institution": "Motilal Nehru National Institute Of Technology",
      "area": "Computer Science",
      "studyType": "Bachelor of Technology - BTech",
      "startDate": "2017-12-31",
      "endDate": "2021-12-31",
      "score": "",
      "courses": [
        "CS 13101 - Data Structures",
        "CS 14101 - Analysis of Algorithms",
        "CS 14103 - Computer Organization",
        "CS 14104 - Automata Theory",
        "CS 15101 - Microprocessor and its application",
        "CS 15103 - Database Management System",
        "CS 15106 - Computer Architecture",
        "CS 16102 - Compiler Construction",
        "CS 16105 - Computer Networks",
        "CS 16103 - Data Mining"
      ]
    }
  ],
  "awards": [
    {
      "title": "Annual Award for CY'22",
      "date": "2023-05-31",
      "awarder": "Myntra Designs Pvt Ltd",
      "summary": "Annual Award in 'Aim High' category."
    },
    {
      "title": "JFM Quarter R&R Award for CY '22",
      "date": "2022-05-31",
      "awarder": "Myntra Designs Pvt Ltd",
      "summary": "Quarter Award in \"Make It Happen\" Category. It is awarded for taking ownership, doing all it takes and driving impactful results with agility."
    },
    {
      "title": "JAS Quarter R&R Award for CY '21",
      "date": "2021-09-30",
      "awarder": "Myntra Designs Pvt Ltd",
      "summary": "Quarter Award in \"Make It Happen\" Category. It is awarded for taking ownership, doing all it takes and driving impactful results with agility."
    },
    {
      "title": "1st Runner up of B-Plan Competition",
      "date": "2021-02-28",
      "awarder": "Entrepreneurship Cell, Miranda House, University of Delhi",
      "summary": ""
    },
    {
      "title": "Best Pitcher in Saudagar",
      "date": "2021-01-31",
      "awarder": "Solaris, IIM Udaipur",
      "summary": ""
    },
    {
      "title": "Winner Of Softablitz",
      "date": "2019-09-30",
      "awarder": "Student Activity Centre NIT Allahabad",
      "summary": "Softablitz is the software development event organized under the annual techno-management event Avishkar at MNNIT Allahabad (Obtained 2nd Prize)"
    },
    {
      "title": "Winner of TuxWars",
      "date": "2019-09-30",
      "awarder": "Student Activity Centre NIT Allahabad",
      "summary": "TuxWars is the Linux based event organized under the annual techno-management event Avishkar at MNNIT Allahabad (Obtained 2nd Prize)"
    },
    {
      "title": "Winner Of Softablitz",
      "date": "2018-09-30",
      "awarder": "Student Activity Centre NIT Allahabad",
      "summary": "Softablitz is the software development event organized under the annual techno-management event Avishkar at MNNIT Allahabad (Obtained 2nd Prize)"
    },
    {
      "title": "Winner of DevJam",
      "date": "2018-04-30",
      "awarder": "Student Activity Centre NIT Allahabad",
      "summary": "DevJam is the software development contest organized under Weekend Of Code by Computer Club MNNIT Allahabad (Obtained 3rd Prize)"
    }
  ],
  "certificates": [
    {
      "name": "Sequence Models",
      "issuer": "DeepLearning.AI",
      "startDate": "2021-03-31",
      "url": "http://coursera.org/verify/PXUZGCYH7C5F"
    },
    {
      "name": "Deep Learning and NLP",
      "issuer": "Udemy",
      "startDate": "2021-03-31",
      "url": "https://www.udemy.com/certificate/UC-7edc739d-dc91-4140-abb6-73b8f351b48b/"
    },
    {
      "name": "Neural Networks and Deep Learning",
      "issuer": "DeepLearning.AI",
      "startDate": "2021-04-30",
      "url": "http://coursera.org/verify/MBCYPF3EHAYH"
    },
    {
      "name": "Improving Deep Neural Networks: Hyperparameter Tuning, Regularization and Optimization",
      "issuer": "DeepLearning.AI",
      "startDate": "2021-05-31",
      "url": "https://www.coursera.org/account/accomplishments/verify/JSR9GXCP9B7T"
    },
    {
      "name": "Structuring Machine Learning Projects",
      "issuer": "DeepLearning.AI",
      "startDate": "2021-06-30",
      "url": "https://coursera.org/verify/NX4HXBDE258Y"
    },
    {
      "name": "Convolutional Neural Networks",
      "issuer": "DeepLearning.AI",
      "startDate": "2021-06-30",
      "url": "https://coursera.org/verify/8LBTXZLPXENQ"
    },
    {
      "name": "Deep Learning Specialization",
      "issuer": "DeepLearning.AI",
      "startDate": "2021-06-30",
      "url": "https://coursera.org/verify/3DLEHQAEWWKF"
    },
    {
      "name": "Build Basic Generative Adversarial Networks (GANs)",
      "issuer": "DeepLearning.AI",
      "startDate": "2021-08-31",
      "url": "https://coursera.org/verify/89EMJRPRKWNJ"
    },
    {
      "name": "Go: The Complete Developer's Guide (Golang)",
      "issuer": "Udemy",
      "startDate": "2021-08-31",
      "url": "https://ude.my/UC-a7b99fc9-469b-4fd9-80bd-cc8516c88401"
    },
    {
      "name": "NVIDIA DLI Certificate – Fundamentals of Accelerated Computing with CUDA Python",
      "issuer": "NVIDIA",
      "startDate": "2021-11-30",
      "url": "https://courses.nvidia.com/certificates/03f64d1f3a6e4e5aa82128474bc968fe"
    }
  ],
  "publications": [
    {
      "name": "Efficient Vector Store System for Python using Shared Memory",
      "publisher": "ACM",
      "releaseDate": "2023-05-16",
      "summary": "Many e-commerce companies use machine learning to make customer experience better. Even within a single company, there will be generally many independent services running, each specializing in some aspect of customer experience. Since machine learning models work on abstract vectors representing users and/or items, each such service needs a way to store these vectors. A common approach nowadays is to save them in in-memory caches like Memcached. As these caches run in their own processes, and Machine Learning services generally run as Python services, there is a communication overhead involved for each request that ML service serves. One can reduce this overhead by directly storing these vectors in a Python dictionary within the service. To support concurrency and scale, a single node runs multiple instances of the same service. Thus, we also want to avoid duplicating these vectors across multiple processes.\n\nIn this paper, we propose a system to store vectors in shared memory and efficiently serve all concurrent instances of the service, without replicating the vectors themselves. We achieve up to 4.5x improvements in latency compared to Memcached. Additionally, due to availability of more memory, we can increase the number of server processes running in each node, translating into greater throughput. We also discuss the impact of the proposed method (towards increasing the throughput) in live production scenario.",
      "url": "https://dl.acm.org/doi/10.1145/3564121.3564799"
    },
    {
      "name": "CLOTON: A GAN based approach for Clothing Try-On",
      "publisher": "IEEE",
      "releaseDate": "2021-10-19",
      "summary": "Cloton is a framework that produces a picture of a person wearing the target clothing while taking into account arbitrary body shapes and poses. As the generation of an individual image necessitates the extraction of body shape and pose from one image and target clothing from another, the architecture is divided into a number of tasks. With these two images as input, the system generates a new picture of the user wearing the target clothing using a generative network. The output is this generated image, which is then sent back to the user. By using encoder-decoder networks as the generator model and training it using the generative adversarial approach used by GANs, Cloton manages to generate visually appealing garment swapped images of the user. Cloton also has good results in the quantitative analysis of the system as compared to previous works.",
      "url": "https://ieeexplore.ieee.org/document/9565973"
    }
  ],
  "languages": [
    {
      "fluency": "Full Professional",
      "language": "English"
    },
    {
      "fluency": "Native Speaker",
      "language": "Hindi"
    }
  ],
  "interests": [],
  "references": [],
  "projects": [
    {
      "name": "College Bot",
      "startDate": "2021-03-31",
      "summary": "An automated chat application based on deep learning to answer the day-to-day basic queries of students, such as information regarding college, Etc.",
      "url": null,
      "endDate": "2021-04-30"
    },
    {
      "name": "Cloton",
      "startDate": "2020-08-31",
      "summary": "A deep learning based framework to give a virtual try room experience for the users. It is built using the principle of Generative Adversarial Networks.",
      "url": "https://github.com/Shreypandey/Cloton",
      "endDate": "2020-11-30"
    },
    {
      "name": "ShareThat",
      "startDate": "2020-02-28",
      "summary": "A Simple JavaFX based Application used to share files and send messages across a common LAN. This Application works on the principle of Socket Programming. It is based on the ShareIt android application.",
      "url": "https://github.com/Shreypandey/ShareThat",
      "endDate": "2020-02-28"
    },
    {
      "name": "Distribution",
      "startDate": "2019-09-30",
      "summary": "A Java based P2P File Sharing Software that works on the principle of BitTorrent with streaming service of media files",
      "url": "https://github.com/Shreypandey/Distribution",
      "endDate": "2019-09-30"
    },
    {
      "name": "Rondeau",
      "startDate": "2019-09-30",
      "summary": "A Java based video call cum messaging application with functionalities of offline messaging, notifications, and Last Seen of user",
      "url": "https://github.com/Shreypandey/Sakshatkar",
      "endDate": "2019-09-30"
    },
    {
      "name": "Smart Ville",
      "startDate": "2019-01-31",
      "summary": "An Interactive Android App with Google Map displaying common potholes and service running in the background to detect the potholes based on readings from Accelerometer, Gyroscope, and Magnetometer. Authorities can interact with the server to get the locations of prominent potholes and repair them.",
      "url": "https://github.com/Shreypandey/Smart_Ville",
      "endDate": "2019-01-31"
    },
    {
      "name": "Sacred Bazaar",
      "startDate": "2018-09-30",
      "summary": "An E-commerce Platform for buying and selling products.",
      "url": "https://github.com/Shreypandey/Sacred-bazaar",
      "endDate": "2018-09-30"
    },
    {
      "name": "Secure Quiz",
      "startDate": "2018-09-30",
      "summary": "A secure platform for quiz where everything is secure and a teacher can add a quiz and multiple students can give the quiz.",
      "url": "https://github.com/Shreypandey/Secure-Quiz",
      "endDate": "2018-09-30"
    },
    {
      "name": "EasyQ",
      "startDate": "2018-04-30",
      "summary": "EasyQ will offer a platform to people to sit where ever they are and not stand in tiresome lines/queues and wait for their turn to come in hospitals, dispensaries, canteens, banks, restaurants, etc where all you need tokens to wait.",
      "url": "https://github.com/Shreypandey/EasyQ",
      "endDate": "2018-04-30"
    },
    {
      "name": "Address Book",
      "startDate": "2017-09-30",
      "summary": "A small desktop application for saving contacts built on Java",
      "url": "https://github.com/Shreypandey/Address-Book",
      "endDate": "2017-09-30"
    }
  ],
  "meta": {
    "version": "v1.0.0",
    "canonical": "https://github.com/jsonresume/resume-schema/blob/v1.0.0/schema.json"
  }
}